{"seed":44272325,"replayData":[{"frame":59,"type":"down","key":"s"},{"frame":73,"type":"down","key":"a"},{"frame":82,"type":"up","key":"s"},{"frame":83,"type":"up","key":"a"},{"frame":106,"type":"down","key":"d"},{"frame":114,"type":"up","key":"d"},{"frame":178,"type":"down","key":"d"},{"frame":194,"type":"up","key":"d"},{"frame":200,"type":"down","key":"a"},{"frame":212,"type":"up","key":"a"},{"frame":266,"type":"down","key":"a"},{"frame":281,"type":"up","key":"a"},{"frame":312,"type":"down","key":"d"},{"frame":327,"type":"up","key":"d"},{"frame":349,"type":"down","key":"d"},{"frame":354,"type":"up","key":"d"},{"frame":363,"type":"down","key":"a"},{"frame":372,"type":"up","key":"a"},{"frame":399,"type":"down","key":"d"},{"frame":408,"type":"up","key":"d"},{"frame":423,"type":"down","key":"a"},{"frame":432,"type":"up","key":"a"},{"frame":464,"type":"down","key":"d"},{"frame":469,"type":"up","key":"d"},{"frame":489,"type":"down","key":"a"},{"frame":496,"type":"up","key":"a"},{"frame":513,"type":"down","key":"d"},{"frame":520,"type":"up","key":"d"},{"frame":563,"type":"down","key":"a"},{"frame":568,"type":"up","key":"a"},{"frame":579,"type":"down","key":"d"},{"frame":588,"type":"up","key":"d"},{"frame":597,"type":"down","key":"a"},{"frame":606,"type":"up","key":"a"},{"frame":711,"type":"down","key":"d"},{"frame":717,"type":"up","key":"d"},{"frame":804,"type":"down","key":"a"},{"frame":812,"type":"up","key":"a"},{"frame":896,"type":"down","key":"d"},{"frame":904,"type":"up","key":"d"},{"frame":989,"type":"down","key":"a"},{"frame":1001,"type":"up","key":"a"},{"frame":1082,"type":"down","key":"d"},{"frame":1094,"type":"up","key":"d"},{"frame":1176,"type":"down","key":"a"},{"frame":1184,"type":"up","key":"a"},{"frame":1207,"type":"down","key":"a"},{"frame":1211,"type":"up","key":"a"},{"frame":1270,"type":"down","key":"d"},{"frame":1281,"type":"up","key":"d"},{"frame":1297,"type":"down","key":"s"},{"frame":1313,"type":"up","key":"s"},{"frame":1336,"type":"down","key":"d"},{"frame":1343,"type":"up","key":"d"},{"frame":1367,"type":"down","key":"s"},{"frame":1374,"type":"up","key":"s"},{"frame":1388,"type":"down","key":"a"},{"frame":1393,"type":"up","key":"a"},{"frame":1398,"type":"down","key":"d"},{"frame":1408,"type":"up","key":"d"},{"frame":1416,"type":"down","key":"a"},{"frame":1423,"type":"up","key":"a"},{"frame":1436,"type":"down","key":"d"},{"frame":1441,"type":"up","key":"d"},{"frame":1455,"type":"down","key":"a"},{"frame":1478,"type":"up","key":"a"},{"frame":1490,"type":"down","key":"a"},{"frame":1495,"type":"up","key":"a"},{"frame":1505,"type":"down","key":"d"},{"frame":1510,"type":"up","key":"d"},{"frame":1518,"type":"down","key":"a"},{"frame":1523,"type":"up","key":"a"},{"frame":1544,"type":"down","key":"d"},{"frame":1551,"type":"up","key":"d"},{"frame":1560,"type":"down","key":"a"},{"frame":1565,"type":"up","key":"a"},{"frame":1569,"type":"down","key":"d"},{"frame":1578,"type":"up","key":"d"},{"frame":1585,"type":"down","key":"a"},{"frame":1602,"type":"up","key":"a"},{"frame":1619,"type":"down","key":"d"},{"frame":1632,"type":"up","key":"d"},{"frame":1658,"type":"down","key":"a"},{"frame":1667,"type":"up","key":"a"},{"frame":1674,"type":"down","key":"a"},{"frame":1683,"type":"up","key":"a"},{"frame":1708,"type":"down","key":"d"},{"frame":1717,"type":"up","key":"d"},{"frame":1743,"type":"down","key":"s"},{"frame":1745,"type":"down","key":"d"},{"frame":1748,"type":"up","key":"s"},{"frame":1750,"type":"up","key":"d"},{"frame":1763,"type":"down","key":"d"},{"frame":1768,"type":"up","key":"d"},{"frame":1782,"type":"down","key":"a"},{"frame":1789,"type":"up","key":"a"},{"frame":1818,"type":"down","key":"a"},{"frame":1848,"type":"up","key":"a"},{"frame":1863,"type":"down","key":"a"},{"frame":1869,"type":"up","key":"a"},{"frame":1880,"type":"down","key":"a"},{"frame":1895,"type":"up","key":"a"},{"frame":1920,"type":"down","key":"a"},{"frame":1923,"type":"up","key":"a"},{"frame":1943,"type":"down","key":"d"},{"frame":1946,"type":"up","key":"d"},{"frame":1971,"type":"down","key":"d"},{"frame":1978,"type":"up","key":"d"},{"frame":1981,"type":"down","key":"d"},{"frame":1988,"type":"up","key":"d"},{"frame":2004,"type":"down","key":"a"},{"frame":2029,"type":"up","key":"a"},{"frame":2041,"type":"down","key":"a"},{"frame":2058,"type":"up","key":"a"},{"frame":2076,"type":"down","key":"d"},{"frame":2093,"type":"up","key":"d"},{"frame":2108,"type":"down","key":"d"},{"frame":2121,"type":"up","key":"d"},{"frame":2149,"type":"down","key":"d"},{"frame":2155,"type":"up","key":"d"},{"frame":2168,"type":"down","key":"d"},{"frame":2175,"type":"up","key":"d"},{"frame":2177,"type":"down","key":"a"},{"frame":2184,"type":"up","key":"a"},{"frame":2210,"type":"down","key":"a"},{"frame":2218,"type":"up","key":"a"},{"frame":2238,"type":"down","key":"a"},{"frame":2244,"type":"up","key":"a"},{"frame":2248,"type":"down","key":"d"},{"frame":2257,"type":"up","key":"d"},{"frame":2269,"type":"down","key":"a"},{"frame":2279,"type":"up","key":"a"},{"frame":2302,"type":"down","key":"d"},{"frame":2312,"type":"up","key":"d"},{"frame":2336,"type":"down","key":"a"},{"frame":2343,"type":"up","key":"a"},{"frame":2373,"type":"down","key":"a"},{"frame":2379,"type":"up","key":"a"},{"frame":2414,"type":"down","key":"d"},{"frame":2423,"type":"up","key":"d"},{"frame":2433,"type":"down","key":"a"},{"frame":2442,"type":"up","key":"a"},{"frame":2511,"type":"down","key":"d"},{"frame":2519,"type":"up","key":"d"},{"frame":2558,"type":"down","key":"d"},{"frame":2559,"type":"up","key":"d"},{"frame":2655,"type":"down","key":"d"},{"frame":2666,"type":"up","key":"d"},{"frame":2715,"type":"down","key":"a"},{"frame":2719,"type":"up","key":"a"},{"frame":2761,"type":"down","key":"a"},{"frame":2770,"type":"up","key":"a"},{"frame":2867,"type":"down","key":"d"},{"frame":2890,"type":"up","key":"d"},{"frame":2945,"type":"down","key":"a"},{"frame":2961,"type":"up","key":"a"},{"frame":3036,"type":"down","key":"a"},{"frame":3046,"type":"up","key":"a"},{"frame":3090,"type":"down","key":"a"},{"frame":3094,"type":"up","key":"a"},{"frame":3108,"type":"down","key":"d"},{"frame":3130,"type":"up","key":"d"},{"frame":3151,"type":"down","key":"w"},{"frame":3163,"type":"down","key":"d"},{"frame":3166,"type":"up","key":"w"},{"frame":3324,"type":"up","key":"d"},{"frame":3460,"type":"down","key":"a"},{"frame":3495,"type":"up","key":"a"},{"frame":3501,"type":"down","key":"a"},{"frame":3510,"type":"up","key":"a"},{"frame":3520,"type":"down","key":"a"},{"frame":3530,"type":"up","key":"a"},{"frame":3590,"type":"down","key":"d"},{"frame":3596,"type":"up","key":"d"},{"frame":3613,"type":"down","key":"a"},{"frame":3625,"type":"up","key":"a"},{"frame":3646,"type":"down","key":"d"},{"frame":3655,"type":"up","key":"d"},{"frame":3709,"type":"down","key":"a"},{"frame":3730,"type":"up","key":"a"},{"frame":3759,"type":"down","key":"d"},{"frame":3782,"type":"down","key":"w"},{"frame":3810,"type":"up","key":"d"},{"frame":3825,"type":"down","key":"a"},{"frame":3830,"type":"up","key":"a"},{"frame":3831,"type":"up","key":"w"},{"frame":3845,"type":"down","key":"a"},{"frame":3891,"type":"up","key":"a"},{"frame":3900,"type":"down","key":"d"},{"frame":3908,"type":"up","key":"d"},{"frame":3928,"type":"down","key":"s"},{"frame":3956,"type":"up","key":"s"},{"frame":4013,"type":"down","key":"a"},{"frame":4058,"type":"up","key":"a"},{"frame":4060,"type":"down","key":"d"},{"frame":4109,"type":"up","key":"d"},{"frame":4109,"type":"down","key":"a"},{"frame":4135,"type":"up","key":"a"},{"frame":4135,"type":"down","key":"d"},{"frame":4150,"type":"up","key":"d"},{"frame":4152,"type":"down","key":"a"},{"frame":4154,"type":"up","key":"a"},{"frame":4192,"type":"down","key":"a"},{"frame":4209,"type":"down","key":"s"},{"frame":4221,"type":"up","key":"s"},{"frame":4239,"type":"down","key":"s"},{"frame":4244,"type":"up","key":"s"},{"frame":4257,"type":"down","key":"s"},{"frame":4263,"type":"up","key":"s"},{"frame":4271,"type":"down","key":"s"},{"frame":4274,"type":"up","key":"s"},{"frame":4293,"type":"down","key":"w"},{"frame":4302,"type":"up","key":"w"},{"frame":4302,"type":"up","key":"a"},{"frame":4302,"type":"down","key":"d"},{"frame":4313,"type":"up","key":"d"},{"frame":4372,"type":"down","key":"a"},{"frame":4389,"type":"up","key":"a"},{"frame":4426,"type":"down","key":"d"},{"frame":4481,"type":"up","key":"d"},{"frame":4482,"type":"down","key":"s"},{"frame":4499,"type":"up","key":"s"},{"frame":4569,"type":"down","key":"d"},{"frame":4575,"type":"up","key":"d"},{"frame":4585,"type":"down","key":"a"},{"frame":4590,"type":"up","key":"a"},{"frame":4627,"type":"down","key":"a"},{"frame":4643,"type":"up","key":"a"},{"frame":4658,"type":"down","key":"a"},{"frame":4679,"type":"up","key":"a"},{"frame":4709,"type":"down","key":"d"},{"frame":4719,"type":"up","key":"d"},{"frame":4782,"type":"down","key":"d"},{"frame":4789,"type":"up","key":"d"},{"frame":4804,"type":"down","key":"d"},{"frame":4808,"type":"up","key":"d"},{"frame":4824,"type":"down","key":"a"},{"frame":4833,"type":"up","key":"a"},{"frame":4854,"type":"down","key":"d"},{"frame":4869,"type":"up","key":"d"},{"frame":4879,"type":"down","key":"a"},{"frame":4904,"type":"up","key":"a"},{"frame":4914,"type":"down","key":"d"},{"frame":4933,"type":"up","key":"d"},{"frame":4948,"type":"down","key":"w"},{"frame":4959,"type":"down","key":"d"},{"frame":4964,"type":"up","key":"w"},{"frame":5066,"type":"up","key":"d"},{"frame":5144,"type":"down","key":"a"},{"frame":5169,"type":"up","key":"a"},{"frame":5207,"type":"down","key":"s"},{"frame":5209,"type":"down","key":"a"},{"frame":5222,"type":"up","key":"s"},{"frame":5223,"type":"up","key":"a"},{"frame":5246,"type":"down","key":"a"},{"frame":5252,"type":"up","key":"a"},{"frame":5277,"type":"down","key":"a"},{"frame":5280,"type":"up","key":"a"},{"frame":5316,"type":"down","key":"a"},{"frame":5321,"type":"up","key":"a"},{"frame":5349,"type":"down","key":"a"},{"frame":5353,"type":"up","key":"a"},{"frame":5356,"type":"down","key":"a"},{"frame":5372,"type":"up","key":"a"},{"frame":5383,"type":"down","key":"a"},{"frame":5417,"type":"up","key":"a"},{"frame":5453,"type":"down","key":"d"},{"frame":5477,"type":"up","key":"d"},{"frame":5488,"type":"down","key":"a"},{"frame":5501,"type":"up","key":"a"},{"frame":5509,"type":"down","key":"a"},{"frame":5519,"type":"up","key":"a"},{"frame":5559,"type":"down","key":"a"},{"frame":5573,"type":"up","key":"a"},{"frame":5662,"type":"down","key":"d"},{"frame":5683,"type":"up","key":"d"},{"frame":5708,"type":"down","key":"d"},{"frame":5720,"type":"up","key":"d"},{"frame":5734,"type":"down","key":"a"},{"frame":5745,"type":"up","key":"a"},{"frame":5784,"type":"down","key":"a"},{"frame":5807,"type":"up","key":"a"},{"frame":5879,"type":"down","key":"d"},{"frame":5902,"type":"up","key":"d"},{"frame":6152,"type":"down","key":"s"},{"frame":6159,"type":"down","key":"a"},{"frame":6162,"type":"up","key":"a"},{"frame":6162,"type":"up","key":"s"},{"frame":6169,"type":"down","key":"a"},{"frame":6187,"type":"up","key":"a"},{"frame":6210,"type":"down","key":"d"},{"frame":6215,"type":"up","key":"d"},{"frame":6221,"type":"down","key":"w"},{"frame":6233,"type":"up","key":"w"},{"frame":6246,"type":"down","key":"d"},{"frame":6249,"type":"up","key":"d"},{"frame":6266,"type":"down","key":"s"},{"frame":6271,"type":"up","key":"s"},{"frame":6323,"type":"down","key":"a"},{"frame":6332,"type":"up","key":"a"},{"frame":6362,"type":"down","key":"d"},{"frame":6370,"type":"up","key":"d"},{"frame":6420,"type":"down","key":"d"},{"frame":6433,"type":"up","key":"d"},{"frame":6464,"type":"down","key":"d"},{"frame":6469,"type":"up","key":"d"},{"frame":6496,"type":"down","key":"a"},{"frame":6502,"type":"up","key":"a"},{"frame":6524,"type":"down","key":"a"},{"frame":6556,"type":"up","key":"a"},{"frame":6582,"type":"down","key":"d"},{"frame":6607,"type":"up","key":"d"},{"frame":6643,"type":"down","key":"s"},{"frame":6652,"type":"down","key":"a"},{"frame":6656,"type":"up","key":"s"},{"frame":6661,"type":"up","key":"a"},{"frame":6669,"type":"down","key":"a"},{"frame":6686,"type":"up","key":"a"},{"frame":6721,"type":"down","key":"a"},{"frame":6726,"type":"up","key":"a"},{"frame":6739,"type":"down","key":"d"},{"frame":6749,"type":"up","key":"d"},{"frame":6766,"type":"down","key":"d"},{"frame":6779,"type":"up","key":"d"},{"frame":6830,"type":"down","key":"d"},{"frame":6836,"type":"up","key":"d"},{"frame":6912,"type":"down","key":"a"},{"frame":6920,"type":"up","key":"a"},{"frame":6953,"type":"down","key":"a"},{"frame":6964,"type":"up","key":"a"},{"frame":6986,"type":"down","key":"d"},{"frame":7006,"type":"up","key":"d"},{"frame":7021,"type":"down","key":"d"},{"frame":7025,"type":"up","key":"d"},{"frame":7033,"type":"down","key":"a"},{"frame":7043,"type":"up","key":"a"},{"frame":7056,"type":"down","key":"a"},{"frame":7063,"type":"up","key":"a"},{"frame":7091,"type":"down","key":"w"},{"frame":7101,"type":"down","key":"a"},{"frame":7121,"type":"up","key":"w"},{"frame":7138,"type":"up","key":"a"},{"frame":7149,"type":"down","key":"w"},{"frame":7212,"type":"down","key":"d"},{"frame":7229,"type":"up","key":"d"},{"frame":7232,"type":"down","key":"d"},{"frame":7252,"type":"up","key":"d"},{"frame":7255,"type":"up","key":"s"},{"frame":7264,"type":"down","key":"a"},{"frame":7264,"type":"down","key":"s"},{"frame":7335,"type":"up","key":"w"},{"frame":7341,"type":"down","key":"s"},{"frame":7344,"type":"up","key":"s"},{"frame":7353,"type":"down","key":"w"},{"frame":7362,"type":"up","key":"w"},{"frame":7363,"type":"down","key":"a"},{"frame":7364,"type":"down","key":"s"},{"frame":7371,"type":"up","key":"a"},{"frame":7415,"type":"up","key":"s"},{"frame":7467,"type":"down","key":"d"},{"frame":7480,"type":"down","key":"s"},{"frame":7487,"type":"up","key":"d"},{"frame":7489,"type":"up","key":"s"},{"frame":7492,"type":"down","key":"a"},{"frame":7499,"type":"up","key":"a"},{"frame":7516,"type":"down","key":"d"},{"frame":7528,"type":"down","key":"s"},{"frame":7537,"type":"up","key":"d"},{"frame":7547,"type":"down","key":"a"},{"frame":7550,"type":"up","key":"s"},{"frame":7569,"type":"up","key":"a"},{"frame":7589,"type":"down","key":"a"},{"frame":7596,"type":"up","key":"a"},{"frame":7626,"type":"down","key":"d"},{"frame":7632,"type":"up","key":"d"},{"frame":7644,"type":"down","key":"a"},{"frame":7651,"type":"up","key":"a"},{"frame":7687,"type":"down","key":"escape"},{"frame":7693,"type":"up","key":"escape"},{"frame":7754,"type":"down","key":"d"},{"frame":7758,"type":"down","key":"w"},{"frame":7819,"type":"up","key":"w"},{"frame":7849,"type":"up","key":"d"},{"frame":7850,"type":"down","key":"w"},{"frame":7851,"type":"down","key":"a"},{"frame":7856,"type":"up","key":"w"},{"frame":7889,"type":"up","key":"a"},{"frame":7890,"type":"down","key":"d"},{"frame":7995,"type":"up","key":"d"},{"frame":7995,"type":"down","key":"a"},{"frame":8115,"type":"up","key":"a"},{"frame":8115,"type":"down","key":"d"}]}